{"OutputFileHashSum":"9BE2B0DDD480B3DDAEFC773F785528F51DB1B04F4018FBA499E462563359D38C","Converted":true,"OutputModifyDate":"2020-08-27T13:35:04.0157907Z","Metadatas":[{"CategoryName":"VuGen.Replay","Offset":528,"Length":23,"TypeId":1},{"CategoryName":"VuGen.Replay","Offset":862,"Length":73,"TypeId":2},{"CategoryName":"VuGen.Replay","Offset":2730,"Length":118,"TypeId":3},{"CategoryName":"VuGen.Replay","Offset":3056,"Length":118,"TypeId":3},{"CategoryName":"VuGen.Replay","Offset":5682,"Length":134,"TypeId":2},{"CategoryName":"VuGen.Replay","Offset":5816,"Length":65,"TypeId":2},{"CategoryName":"VuGen.Replay","Offset":10537,"Length":121,"TypeId":3},{"CategoryName":"VuGen.Replay","Offset":11455,"Length":123,"TypeId":2},{"CategoryName":"VuGen.Replay","Offset":11578,"Length":78,"TypeId":2},{"CategoryName":"VuGen.Replay","Offset":25846,"Length":138,"TypeId":2},{"CategoryName":"VuGen.Replay","Offset":25984,"Length":90,"TypeId":2},{"CategoryName":"VuGen.Replay","Offset":26164,"Length":122,"TypeId":3},{"CategoryName":"VuGen.Replay","Offset":36913,"Length":149,"TypeId":2},{"CategoryName":"VuGen.Replay","Offset":37062,"Length":72,"TypeId":2},{"CategoryName":"VuGen.Replay","Offset":38535,"Length":130,"TypeId":2},{"CategoryName":"VuGen.Replay","Offset":38665,"Length":77,"TypeId":2},{"CategoryName":"VuGen.Replay","Offset":46153,"Length":136,"TypeId":2},{"CategoryName":"VuGen.Replay","Offset":46289,"Length":65,"TypeId":2},{"CategoryName":"VuGen.Replay","Offset":51365,"Length":123,"TypeId":2},{"CategoryName":"VuGen.Replay","Offset":51488,"Length":72,"TypeId":2},{"CategoryName":"VuGen.Replay","Offset":51560,"Length":110,"TypeId":2},{"CategoryName":"VuGen.Replay","Offset":51670,"Length":88,"TypeId":2},{"CategoryName":"VuGen.Replay","Offset":53062,"Length":122,"TypeId":3},{"CategoryName":"VuGen.Replay","Offset":53941,"Length":225,"TypeId":3},{"CategoryName":"VuGen.Replay","Offset":59418,"Length":146,"TypeId":2},{"CategoryName":"VuGen.Replay","Offset":59564,"Length":70,"TypeId":2},{"CategoryName":"VuGen.Replay","Offset":65394,"Length":128,"TypeId":2},{"CategoryName":"VuGen.Replay","Offset":65522,"Length":76,"TypeId":2},{"CategoryName":"VuGen.Replay","Offset":66988,"Length":225,"TypeId":3},{"CategoryName":"VuGen.Replay","Offset":67496,"Length":134,"TypeId":2},{"CategoryName":"VuGen.Replay","Offset":67630,"Length":67,"TypeId":2},{"CategoryName":"VuGen.Replay","Offset":68529,"Length":125,"TypeId":2},{"CategoryName":"VuGen.Replay","Offset":68677,"Length":21,"TypeId":1},{"CategoryName":"VuGen.Replay","Offset":68698,"Length":23,"TypeId":1},{"CategoryName":"VuGen.Replay","Offset":69032,"Length":73,"TypeId":2},{"CategoryName":"VuGen.Replay","Offset":70900,"Length":118,"TypeId":3},{"CategoryName":"VuGen.Replay","Offset":71226,"Length":118,"TypeId":3},{"CategoryName":"VuGen.Replay","Offset":74336,"Length":133,"TypeId":2},{"CategoryName":"VuGen.Replay","Offset":74469,"Length":65,"TypeId":2},{"CategoryName":"VuGen.Replay","Offset":79796,"Length":121,"TypeId":3},{"CategoryName":"VuGen.Replay","Offset":80714,"Length":123,"TypeId":2},{"CategoryName":"VuGen.Replay","Offset":80837,"Length":78,"TypeId":2},{"CategoryName":"VuGen.Replay","Offset":95914,"Length":138,"TypeId":2},{"CategoryName":"VuGen.Replay","Offset":96052,"Length":90,"TypeId":2},{"CategoryName":"VuGen.Replay","Offset":96232,"Length":122,"TypeId":3},{"CategoryName":"VuGen.Replay","Offset":107180,"Length":149,"TypeId":2},{"CategoryName":"VuGen.Replay","Offset":107329,"Length":72,"TypeId":2},{"CategoryName":"VuGen.Replay","Offset":108802,"Length":130,"TypeId":2},{"CategoryName":"VuGen.Replay","Offset":108932,"Length":77,"TypeId":2},{"CategoryName":"VuGen.Replay","Offset":116574,"Length":136,"TypeId":2},{"CategoryName":"VuGen.Replay","Offset":116710,"Length":65,"TypeId":2},{"CategoryName":"VuGen.Replay","Offset":121786,"Length":123,"TypeId":2},{"CategoryName":"VuGen.Replay","Offset":121909,"Length":72,"TypeId":2},{"CategoryName":"VuGen.Replay","Offset":121981,"Length":110,"TypeId":2},{"CategoryName":"VuGen.Replay","Offset":122091,"Length":88,"TypeId":2},{"CategoryName":"VuGen.Replay","Offset":123483,"Length":122,"TypeId":3},{"CategoryName":"VuGen.Replay","Offset":124362,"Length":225,"TypeId":3},{"CategoryName":"VuGen.Replay","Offset":129839,"Length":146,"TypeId":2},{"CategoryName":"VuGen.Replay","Offset":129985,"Length":70,"TypeId":2},{"CategoryName":"VuGen.Replay","Offset":135815,"Length":128,"TypeId":2},{"CategoryName":"VuGen.Replay","Offset":135943,"Length":76,"TypeId":2},{"CategoryName":"VuGen.Replay","Offset":137409,"Length":225,"TypeId":3},{"CategoryName":"VuGen.Replay","Offset":137962,"Length":134,"TypeId":2},{"CategoryName":"VuGen.Replay","Offset":138096,"Length":67,"TypeId":2},{"CategoryName":"VuGen.Replay","Offset":138995,"Length":125,"TypeId":2},{"CategoryName":"VuGen.Replay","Offset":139143,"Length":21,"TypeId":1},{"CategoryName":"VuGen.Replay","Offset":139164,"Length":23,"TypeId":1},{"CategoryName":"VuGen.Replay","Offset":139498,"Length":73,"TypeId":2},{"CategoryName":"VuGen.Replay","Offset":141366,"Length":118,"TypeId":3},{"CategoryName":"VuGen.Replay","Offset":141692,"Length":118,"TypeId":3},{"CategoryName":"VuGen.Replay","Offset":144802,"Length":133,"TypeId":2},{"CategoryName":"VuGen.Replay","Offset":144935,"Length":65,"TypeId":2},{"CategoryName":"VuGen.Replay","Offset":150262,"Length":121,"TypeId":3},{"CategoryName":"VuGen.Replay","Offset":151180,"Length":123,"TypeId":2},{"CategoryName":"VuGen.Replay","Offset":151303,"Length":78,"TypeId":2},{"CategoryName":"VuGen.Replay","Offset":166380,"Length":138,"TypeId":2},{"CategoryName":"VuGen.Replay","Offset":166518,"Length":90,"TypeId":2},{"CategoryName":"VuGen.Replay","Offset":166698,"Length":122,"TypeId":3},{"CategoryName":"VuGen.Replay","Offset":177646,"Length":149,"TypeId":2},{"CategoryName":"VuGen.Replay","Offset":177795,"Length":72,"TypeId":2},{"CategoryName":"VuGen.Replay","Offset":179268,"Length":130,"TypeId":2},{"CategoryName":"VuGen.Replay","Offset":179398,"Length":77,"TypeId":2},{"CategoryName":"VuGen.Replay","Offset":187040,"Length":135,"TypeId":2},{"CategoryName":"VuGen.Replay","Offset":187175,"Length":65,"TypeId":2},{"CategoryName":"VuGen.Replay","Offset":192251,"Length":123,"TypeId":2},{"CategoryName":"VuGen.Replay","Offset":192374,"Length":72,"TypeId":2},{"CategoryName":"VuGen.Replay","Offset":192446,"Length":110,"TypeId":2},{"CategoryName":"VuGen.Replay","Offset":192556,"Length":88,"TypeId":2},{"CategoryName":"VuGen.Replay","Offset":193948,"Length":122,"TypeId":3},{"CategoryName":"VuGen.Replay","Offset":194827,"Length":225,"TypeId":3},{"CategoryName":"VuGen.Replay","Offset":200304,"Length":146,"TypeId":2},{"CategoryName":"VuGen.Replay","Offset":200450,"Length":70,"TypeId":2},{"CategoryName":"VuGen.Replay","Offset":206280,"Length":128,"TypeId":2},{"CategoryName":"VuGen.Replay","Offset":206408,"Length":76,"TypeId":2},{"CategoryName":"VuGen.Replay","Offset":207874,"Length":225,"TypeId":3},{"CategoryName":"VuGen.Replay","Offset":208427,"Length":134,"TypeId":2},{"CategoryName":"VuGen.Replay","Offset":208561,"Length":67,"TypeId":2},{"CategoryName":"VuGen.Replay","Offset":209460,"Length":125,"TypeId":2},{"CategoryName":"VuGen.Replay","Offset":209608,"Length":21,"TypeId":1}],"MetadataTypes":[{"CategoryName":"VuGen.Replay","MetadataTypeName":"HP.LR.Vugen.Iteration","Id":1},{"CategoryName":"VuGen.Replay","MetadataTypeName":"HP.LR.Vugen.NotifyTransaction","Id":2},{"CategoryName":"VuGen.Replay","MetadataTypeName":"Utt.Debugger.Warning","Id":3},{"CategoryName":"VuGen.Replay","MetadataTypeName":"Utt.Debugger.Error","Id":4},{"CategoryName":"VuGen.Replay","MetadataTypeName":"HP.LR.Vugen.NotifyAny","Id":5}]}